{
    "code":0,
    "message":"134123",
    "data":[
        {
            "hospitalId":"1001",
            "hospitalName":"青岛市中心医院",
            "province":"山东省",
            "city":"青岛市"
        },
        {
            "hospitalId":"1002",
            "hospitalName":"北京协和医院",
            "province":"北京市",
            "city":"北京市辖区"
        },
        {
            "hospitalId":"1003",
            "hospitalName":"齐鲁医院",
            "province":"山东省",
            "city":"济南"
        },
        {
            "hospitalId":"1004",
            "hospitalName":"青岛市妇幼医院",
            "province":"山东省",
            "city":"青岛市"
        },
        {
            "hospitalId":"1005",
            "hospitalName":"淄博妇幼医院",
            "province":"山东省",
            "city":"淄博市"
        },
        {
            "hospitalId":"1006",
            "hospitalName":"石家庄市妇幼医院",
            "province":"河北省",
            "city":"石家庄市"
        },
        {
            "hospitalId":"1007",
            "hospitalName":"唐山市妇幼医院",
            "province":"河北省",
            "city":"唐山市"
        },
        {
            "hospitalId":"1008",
            "hospitalName":"太原市妇幼医院",
            "province":"山西省",
            "city":"太原市"
        },
        {
            "hospitalId":"1009",
            "hospitalName":"沈阳市妇幼医院",
            "province":"辽宁省",
            "city":"沈阳市"
        },
        {
            "hospitalId":"1010",
            "hospitalName":"长春市妇幼医院",
            "province":"吉林省",
            "city":"长春市"
        },
        {
            "hospitalId":"1011",
            "hospitalName":"青岛市立医院",
            "province":"山东省",
            "city":"青岛市"
        }
    ]
}